dbt_client/__init__.py
dbt_client/dbt_client.py
dbt_client-0.1.3.dist-info/LICENSE
dbt_client-0.1.3.dist-info/WHEEL
dbt_client-0.1.3.dist-info/METADATA
dbt_client-0.1.3.dist-info/RECORD
